LICENSE
pytcm/__init__.py
pytcm/command.py
pytcm/options.py
pytcm/utils.py
pytcm-0.5.6.dist-info/LICENSE
pytcm-0.5.6.dist-info/WHEEL
pytcm-0.5.6.dist-info/METADATA
pytcm-0.5.6.dist-info/RECORD
