Metadata-Version: 2.1
Name: pytcm
Version: 0.5.6
Summary: pytcm - Python Terminal Commands Manager
Home-page: https://github.com/alexisbeaulieu97/pytcm
License: MIT
Author: Alexis Beaulieu
Author-email: alexisbeaulieu97@gmail.com
Requires-Python: >=3.8,<4.0
Classifier: License :: OSI Approved :: MIT License
Classifier: Programming Language :: Python :: 3
Classifier: Programming Language :: Python :: 3.10
Classifier: Programming Language :: Python :: 3.8
Classifier: Programming Language :: Python :: 3.9
Project-URL: Changelog, https://github.com/alexisbeaulieu97/pytcm/blob/main/CHANGELOG.md
Project-URL: Repository, https://github.com/alexisbeaulieu97/pytcm
